knowai/__init__.py
knowai/agent.py
knowai/cli.py
knowai/cli_vectorstore.py
knowai/core.py
knowai/errors.py
knowai/nodes.py
knowai/prompts.py
knowai/utils.py
knowai/vectorstore.py
knowai-0.5.0.dist-info/METADATA
knowai-0.5.0.dist-info/WHEEL
knowai-0.5.0.dist-info/licenses/LICENSE
knowai-0.5.0.dist-info/RECORD
