Metadata-Version: 2.4
Name: knowai
Version: 0.5.0
Summary: A conversational RAG agent pipeline using LangGraph
Project-URL: Repository, https://github.com/crvernon/knowai
Author-email: "Chris R. Vernon" <chris.vernon@pnnl.gov>
Maintainer-email: Chris Vernon <chris.vernon@pnnl.gov>
License: BSD 3-Clause License
License-File: LICENSE
Classifier: Operating System :: OS Independent
Classifier: Programming Language :: Python :: 3.11
Classifier: Programming Language :: Python :: 3.12
Classifier: Programming Language :: Python :: 3.13
Requires-Python: >=3.11
Requires-Dist: boto3==1.39.1
Requires-Dist: faiss-cpu==1.11.0
Requires-Dist: fastapi==0.115.14
Requires-Dist: langchain-community==0.3.26
Requires-Dist: langchain-core==0.3.67
Requires-Dist: langchain-openai==0.3.27
Requires-Dist: langchain==0.3.26
Requires-Dist: langgraph==0.5.0
Requires-Dist: pandas>=1.5.0
Requires-Dist: pydantic==2.11.7
Requires-Dist: pymupdf==1.26.1
Requires-Dist: python-dotenv==1.1.1
Requires-Dist: streamlit==1.46.1
Requires-Dist: tiktoken==0.9.0
Requires-Dist: tqdm>=4.64.0
Requires-Dist: uvicorn==0.35.0
Provides-Extra: deploy
Requires-Dist: twine>=4.0.1; extra == 'deploy'
Provides-Extra: dev
Requires-Dist: pytest-cov>=2.12.1; extra == 'dev'
Requires-Dist: pytest>=6.0; extra == 'dev'
Requires-Dist: trio>=0.30.0; extra == 'dev'
Provides-Extra: docs
Requires-Dist: autodoc>=0.5.0; extra == 'docs'
Requires-Dist: build>=0.5.1; extra == 'docs'
Requires-Dist: ipykernel>=6.15.1; extra == 'docs'
Requires-Dist: nbsphinx~=0.8.6; extra == 'docs'
Requires-Dist: setuptools>=57.0.0; extra == 'docs'
Requires-Dist: sphinx~=7.2.6; extra == 'docs'
